pygments_redis/__init__.py
pygments_redis/redis.py
pygments_redis-0.2.dist-info/LICENSE
pygments_redis-0.2.dist-info/METADATA
pygments_redis-0.2.dist-info/WHEEL
pygments_redis-0.2.dist-info/entry_points.txt
pygments_redis-0.2.dist-info/top_level.txt
pygments_redis-0.2.dist-info/RECORD
